{"/_app":"pages/_app.js","/_error":"pages/_error.js","/admin/projects/new":"pages/admin/projects/new.html","/admin/signup":"pages/admin/signup.html","/admin/login":"pages/admin/login.html","/api/auth/change-password":"pages/api/auth/change-password.js","/api/links/complete":"pages/api/links/complete.js","/api/links/flag":"pages/api/links/flag.js","/admin/verify":"pages/admin/verify.html","/api/auth/get-id-token":"pages/api/auth/get-id-token.js","/api/links/update-status":"pages/api/links/update-status.js","/api/vendors/create":"pages/api/vendors/create.js","/api/links/generate":"pages/api/links/generate.js","/api/vendors/delete":"pages/api/vendors/delete.js","/api/vendors/list":"pages/api/vendors/list.js","/api/projects/delete":"pages/api/projects/delete.js","/api/verify/captcha":"pages/api/verify/captcha.js","/api/projects/[id]/export":"pages/api/projects/[id]/export.js","/survey/outcome/disqualified":"pages/survey/outcome/disqualified.html","/":"pages/index.html","/survey/outcome/quota-full":"pages/survey/outcome/quota-full.html","/api/projects/[id]/questions":"pages/api/projects/[id]/questions.js","/api/projects/create":"pages/api/projects/create.js","/admin":"pages/admin.js","/admin/projects/[id]":"pages/admin/projects/[id].js","/admin/projects/[id]/questions":"pages/admin/projects/[id]/questions.js","/completion/[projectId]/[uid]":"pages/completion/[projectId]/[uid].js","/completion/[projectId]":"pages/completion/[projectId].js","/s/[projectId]/[uid]":"pages/s/[projectId]/[uid].js","/admin/projects/[id]/generate":"pages/admin/projects/[id]/generate.js","/survey/[projectId]/[uid]":"pages/survey/[projectId]/[uid].js","/admin/projects/[id]/analytics":"pages/admin/projects/[id]/analytics.js","/_document":"pages/_document.js","/404":"pages/404.html"}